i3drsgm/__init__.py
i3drsgm-1.0.9.dist-info/METADATA
i3drsgm-1.0.9.dist-info/WHEEL
i3drsgm-1.0.9.dist-info/top_level.txt
i3drsgm-1.0.9.dist-info/RECORD
