Metadata-Version: 2.1
Name: i3drsgm
Version: 1.0.9
Summary: Python wrapper for I3DR Semi-Global Matcher
Home-page: https://github.com/i3drobotics/pyi3drsgm
Author: Ben Knight
Author-email: bknight@i3drobotics.com
License: UNKNOWN
Platform: UNKNOWN
Classifier: Programming Language :: Python :: 3
Classifier: License :: OSI Approved :: MIT License
Classifier: Operating System :: Microsoft :: Windows
Requires-Python: >=3.6
Requires-Dist: opencv-python
Requires-Dist: stereo3d (>=0.0.3)
Requires-Dist: wget
Requires-Dist: numpy ; python_version == "3.5"
Requires-Dist: numpy (==1.19.3) ; python_version > "3.5"
